{"YMEzI+RARprmm/Zgwh6PhQ==":"untitled-1ssss-2000x782.png","iNk5752wGpRD1I6qz+eGTA==":"untitled-1l-2000x782.png","ig8ycAIWm9O94hmYJM8Kjg==":"untitled-1l-327x128.png","NB74dxzshK9ndgShHoE73w==":"untitled-2000x1208.png","XrKrXrDhbBCCfeHK+0aCVg==":"untitled-1-2000x1208.png","QHXOT2vGis552Dn+v9EoMQ==":"eartistic_logo-265x73.png","pWnLBD6xSunJh3uh77bSdg==":"mbr-2000x1333.jpg","011H6q9+MqvbDTS/SciwLg==":"mbr-2000x1328.jpg","UmktlAkL9SI9v9QdS4a2Zw==":"mbr-1620x1080.jpg","WzmWne8ATfMLVWX3WrFNLg==":"slide1-720x540.jpg","3s8EmvoMXt90VtcQsszatA==":"i-richment-265x52.png","ZUIgn9FJwpJwKRo9WbbgFA==":"i-richment-1400x276.jpg","DUrRafERVevXzmEFiPB5Kw==":"screen%20shot%202017-07-30%20at%201.35.53%20pm-1366x768.png","lTIm/LHEvN6tRED7MDlx0w==":"fizi%20colorful-1754x1240.jpg","3gQw/bcE91vXklYsf8J3gg==":"fizi%20colorful2-2000x1414.jpg","X4r/LsAwBpBIFTVRKK27+A==":"2nd%20page%20website%20blue-2000x1414.jpg","mH22Y5tjLxxnmT/XUr7niw==":"2nd%20page%20website%20blue-2000x1412.jpg","xWkRPh38UR9PdYAqQLC8rA==":"fizi%20colorful2-2000x1414.jpg","/EhgwjVFjxbQ3fFS8YmM4Q==":"2nd%20page%20website%20blue-2000x1412.jpg","K4qs3+9w3eLPw/KcL7TrrQ==":"eartistic%20team%202016-1400x916.jpg","lu0iies5jcY04Dam3Vp8Jg==":"screen%20shot%202017-07-30%20at%201.35.53%20pm-1366x768.png","/2jIaX0XgMhK/ghgsb8dAg==":"3rd%20page%20website%20pink-2000x1413.jpg","lkwPLAkFMRJij5CGfqlKCQ==":"fizi%20colorful-1754x1240.jpg","vOFohJ8Rmislzt6wqX38xQ==":"i-richment-265x52.png","8Qxg5ZLc/GWuAQQRCWt2Lg==":"background.svg","meEzB9Z3ldp2o7r58UVfWA==":"logo-464x128.png","oVf4MaXTKcF8ilmsjqKKWw==":"logo-1-464x128.png","D7lc0rZh7hx9hfWiaxiWaQ==":"background-1.svg","z9UvkHYfTGs8uD0E4qgVpA==":"background-2.svg","THh9k7txVbeUnr3UC0tENQ==":"footer.svg","/wyaoJs9PDHrZyFG+u8t1w==":"sky-ext.svg","bAKXJJQ5MC2B/+IK4V5jnA==":"header.svg","5F11zbKoH1Oyi8KlcXmcuw==":"header-1.svg","2ME5WuG7RgYUqTJEG3ftkg==":"sky.svg","cS+jCqPVnN45gMhcPZtoQQ==":"sky-1.svg","qgs0qb5pyIsgdrGf33xQOg==":"logo-265x72.png","+9zznV+yXrknM3sz6LSTKQ==":"sky-2.svg","+5r2NdBQiMZQtr+ngY8lYg==":"sky-3.svg","W4ElJlmNecYoMgRHxH4BmA==":"footer-1.svg","Y6xzu4Xw9umuJsAAOAvmXg==":"footer-2.svg","1lamSmURg9+eg/w2ZK7QTQ==":"sky-4.svg","C8QBhIAzt3/lsnKwmRtckw==":"sky-5.svg","+AcNsOf8KHaVYNOx+POzNA==":"footer-3.svg","lOdk8A4ZttqD5E1a5haJuQ==":"footer-4.svg"}